mara_metabase/__init__.py
mara_metabase/acl.py
mara_metabase/cli.py
mara_metabase/client.py
mara_metabase/config.py
mara_metabase/metadata.py
mara_metabase/setup.py
mara_metabase/views.py
mara_metabase-2.0.1.dist-info/LICENSE
mara_metabase-2.0.1.dist-info/METADATA
mara_metabase-2.0.1.dist-info/WHEEL
mara_metabase-2.0.1.dist-info/top_level.txt
mara_metabase-2.0.1.dist-info/RECORD
