Metadata-Version: 2.1
Name: mara-metabase
Version: 2.0.1
Summary: Configuring Metabase from Python
Home-page: https://github.com/mara/mara-metabase
Author: Mara contributors
License: MIT
Requires-Python: >=3.6
License-File: LICENSE
Requires-Dist: mara-db (>=4.7.1)
Requires-Dist: mara-page
Requires-Dist: sympy
Requires-Dist: bcrypt
Requires-Dist: requests
